<?xml version="1.0"?>
<!DOCTYPE hibernate-mapping PUBLIC "-//Hibernate/Hibernate Mapping DTD 3.0//EN"
"http://hibernate.sourceforge.net/hibernate-mapping-3.0.dtd">
<!-- Generated Apr 27, 2013 2:07:58 PM by Hibernate Tools 4.0.0 -->
<hibernate-mapping>
    <class name="cvsanaly.Metrics" table="metrics" catalog="cvsanaly">
        <id name="id" type="int">
            <column name="id" />
            <generator class="assigned" />
        </id>
        <property name="fileId" type="java.lang.Integer">
            <column name="file_id" />
        </property>
        <property name="commitId" type="java.lang.Integer">
            <column name="commit_id" />
        </property>
        <property name="lang" type="string">
            <column name="lang" />
        </property>
        <property name="sloc" type="java.lang.Integer">
            <column name="sloc" />
        </property>
        <property name="loc" type="java.lang.Integer">
            <column name="loc" />
        </property>
        <property name="ncomment" type="java.lang.Integer">
            <column name="ncomment" />
        </property>
        <property name="lcomment" type="java.lang.Integer">
            <column name="lcomment" />
        </property>
        <property name="lblank" type="java.lang.Integer">
            <column name="lblank" />
        </property>
        <property name="nfunctions" type="java.lang.Integer">
            <column name="nfunctions" />
        </property>
        <property name="mccabeMax" type="java.lang.Integer">
            <column name="mccabe_max" />
        </property>
        <property name="mccabeMin" type="java.lang.Integer">
            <column name="mccabe_min" />
        </property>
        <property name="mccabeSum" type="java.lang.Integer">
            <column name="mccabe_sum" />
        </property>
        <property name="mccabeMean" type="java.lang.Integer">
            <column name="mccabe_mean" />
        </property>
        <property name="mccabeMedian" type="java.lang.Integer">
            <column name="mccabe_median" />
        </property>
        <property name="halsteadLength" type="java.lang.Integer">
            <column name="halstead_length" />
        </property>
        <property name="halsteadVol" type="java.lang.Integer">
            <column name="halstead_vol" />
        </property>
        <property name="halsteadLevel" type="java.lang.Double">
            <column name="halstead_level" precision="22" scale="0" />
        </property>
        <property name="halsteadMd" type="java.lang.Integer">
            <column name="halstead_md" />
        </property>
    </class>
</hibernate-mapping>
